Metadata-Version: 2.4
Name: bvalcalc
Version: 1.3.0
Summary: Calculate relative diversity (B) under background selection
Author-email: Jacob Marsh <jacob.marsh@unc.edu>, Parul Johri <pjohri@unc.edu>
License:                     GNU GENERAL PUBLIC LICENSE
Project-URL: Homepage, https://github.com/JohriLab/Bvalcalc
Project-URL: Documentation, https://JohriLab.github.io/Bvalcalc
Project-URL: Source, https://github.com/JohriLab/Bvalcalc
Project-URL: Tracker, https://github.com/JohriLab/Bvalcalc/issues
Classifier: Development Status :: 5 - Production/Stable
Classifier: Intended Audience :: Science/Research
Classifier: Topic :: Scientific/Engineering :: Bio-Informatics
Classifier: License :: OSI Approved :: GNU General Public License v3 (GPLv3)
Classifier: Programming Language :: Python :: 3
Classifier: Programming Language :: Python :: 3.8
Classifier: Programming Language :: Python :: 3.9
Classifier: Programming Language :: Python :: 3.10
Classifier: Operating System :: OS Independent
Requires-Python: >=3.10
License-File: LICENSE
Requires-Dist: numpy>=1.22
Requires-Dist: scipy>=1.13
Requires-Dist: matplotlib
Requires-Dist: seaborn<0.14.0,>=0.13.2
Provides-Extra: docs
Requires-Dist: sphinx>=6.0; extra == "docs"
Requires-Dist: sphinx-rtd-theme; extra == "docs"
Provides-Extra: test
Requires-Dist: pytest>=7.0; extra == "test"
Dynamic: license-file
